ecg_k_fold/__init__.py
ecg_k_fold-0.1.3.dist-info/licenses/LICENSE
ecg_k_fold-0.1.3.dist-info/METADATA
ecg_k_fold-0.1.3.dist-info/WHEEL
ecg_k_fold-0.1.3.dist-info/top_level.txt
ecg_k_fold-0.1.3.dist-info/RECORD
